MANIFEST.in
README.txt
setup.py
konami/__init__.py
konami.egg-info/PKG-INFO
konami.egg-info/SOURCES.txt
konami.egg-info/dependency_links.txt
konami.egg-info/top_level.txt